zzd/__init__.py
zzd/auprc_curve.py
zzd/auroc_curve.py
zzd/curve_train_hist.py
zzd/metrics.py
zzd/scores.py
zzd/encode/__init__.py
zzd/encode/ac.py
zzd/encode/cksaap.py
zzd/encode/ct.py
zzd/encode/dpc.py
zzd/encode/pdb2dpc.py
zzd/encode/pdb2graph.py
zzd/feature_encode/__init__.py
zzd/feature_encode/ac.py
zzd/feature_encode/ara_net_node2vec.py
zzd/feature_encode/ara_net_property.py
zzd/feature_encode/ara_node2vec.py
zzd/feature_encode/cksaap.py
zzd/feature_encode/ct.py
zzd/feature_encode/dpc.py
zzd/feature_encode/encodes.py
zzd/feature_encode/esm_mean.py
zzd/feature_encode/feature_combine.py
zzd/feature_encode/onehot.py
zzd/feature_encode/pdb2dpc.py
zzd/feature_encode/pdb2graph.py
zzd/feature_encode/pdb2graph_atom.py
zzd/feature_encode/pdb2graph_atom_surface.py
zzd/feature_encode/pdb2graph_rd2.py
zzd/feature_encode/pdb2graph_surface.py
zzd/feature_encode/pdb2graph_surface_atom.py
zzd/feature_encode/pdb2graph_surface_rd2.py
zzd/feature_encode/personal_features.py
zzd/feature_encode/prottrans.py
zzd/methods/RF.py
zzd/methods/RandomForest.py
zzd/methods/__init__.py
zzd/methods/ddi.py
zzd/methods/dmi.py
zzd/methods/interolog.py
zzd/methods/ppi.py
zzd/methods/ppi_bayesian.py
zzd/methods/ppi_cnn.py
zzd/methods/ppi_cnn_onehot.py
zzd/methods/ppi_cnn_onehot2.py
zzd/methods/ppi_cnn_onehot_2.py
zzd/methods/ppi_cnn_onehot_torch.py
zzd/methods/ppi_cnn_onehot_torch2.py
zzd/methods/ppi_ddi.py
zzd/methods/ppi_interolog.py
zzd/methods/ppi_knn.py
zzd/methods/ppi_logistic.py
zzd/methods/ppi_methods.py
zzd/methods/ppi_predction.py
zzd/methods/ppi_randomforest.py
zzd/methods/ppi_randomforest_test.py
zzd/methods/ppi_svm.py
zzd/methods/ppi_xgboost.py
zzd/methods/randomforest.py
zzd/models/RandomForest.py
zzd/models/__init__.py
zzd/models/bayesian.py
zzd/models/cnn_pytorch.py
zzd/models/cnn_tf.py
zzd/models/knn.py
zzd/models/tf_cnn.py
zzd/models/torch_cnn.py
zzd/tensorflow_models/__init__.py
zzd/tensorflow_models/cnn.py
zzd/utils/__init__.py
zzd/utils/assess.py
zzd/utils/auprc_curve.py
zzd-1.0.5.dist-info/LICENSE
zzd-1.0.5.dist-info/METADATA
zzd-1.0.5.dist-info/WHEEL
zzd-1.0.5.dist-info/top_level.txt
zzd-1.0.5.dist-info/RECORD
