Metadata-Version: 2.1
Name: zzd
Version: 1.0.5
Summary: some tools
Home-page: https://github.com/miderxi/zzd_lib
Author: ChenPing L
Author-email: 1965770446@qq.com
Classifier: Programming Language :: Python :: 3
Classifier: License :: OSI Approved :: MIT License
Classifier: Operating System :: OS Independent
License-File: LICENSE
